sas_yolov7_pose/__init__.py
sas_yolov7_pose/cfg/yolov7-w6-pose.yaml
sas_yolov7_pose/data/coco_kpts.yaml
sas_yolov7_pose/data/coco_kpts_128.yaml
sas_yolov7_pose/data/hyp.pose.yaml
sas_yolov7_pose/data/scripts/get_coco.sh
sas_yolov7_pose/data/scripts/get_voc.sh
sas_yolov7_pose/models/__init__.py
sas_yolov7_pose/models/common.py
sas_yolov7_pose/models/experimental.py
sas_yolov7_pose/models/export.py
sas_yolov7_pose/models/yolo.py
sas_yolov7_pose/models/hub/yolov3-spp.yaml
sas_yolov7_pose/models/hub/yolov3-tiny.yaml
sas_yolov7_pose/models/hub/yolov3.yaml
sas_yolov7_pose/utils/__init__.py
sas_yolov7_pose/utils/activations.py
sas_yolov7_pose/utils/autoanchor.py
sas_yolov7_pose/utils/datasets.py
sas_yolov7_pose/utils/general.py
sas_yolov7_pose/utils/google_utils.py
sas_yolov7_pose/utils/loss.py
sas_yolov7_pose/utils/metrics.py
sas_yolov7_pose/utils/plots.py
sas_yolov7_pose/utils/torch_utils.py
sas_yolov7_pose/utils/aws/__init__.py
sas_yolov7_pose/utils/aws/mime.sh
sas_yolov7_pose/utils/aws/resume.py
sas_yolov7_pose/utils/aws/userdata.sh
sas_yolov7_pose/utils/figures/000000390555_AE.jpg
sas_yolov7_pose/utils/figures/000000390555_YP.jpg
sas_yolov7_pose/utils/figures/AP50_GMACS_val.png
sas_yolov7_pose/utils/figures/AdobeStock.gif
sas_yolov7_pose/utils/flask_rest_api/README.md
sas_yolov7_pose/utils/google_app_engine/Dockerfile
sas_yolov7_pose/utils/google_app_engine/additional_requirements.txt
sas_yolov7_pose/utils/google_app_engine/app.yaml
sas_yolov7_pose/utils/wandb_logging/__init__.py
sas_yolov7_pose/utils/wandb_logging/log_dataset.py
sas_yolov7_pose/utils/wandb_logging/wandb_utils.py
sas_yolov7_pose-1.0.2.dist-info/LICENSE
sas_yolov7_pose-1.0.2.dist-info/LICENSE.md
sas_yolov7_pose-1.0.2.dist-info/METADATA
sas_yolov7_pose-1.0.2.dist-info/WHEEL
sas_yolov7_pose-1.0.2.dist-info/top_level.txt
sas_yolov7_pose-1.0.2.dist-info/RECORD
